{
  "project_info": {
    "project_number": "649679824368",
    "firebase_url": "https://tripplanner-3b1ef.firebaseio.com",
    "project_id": "tripplanner-3b1ef",
    "storage_bucket": "tripplanner-3b1ef.appspot.com"
  },
  "client": [
    {
      "client_info": {
        "mobilesdk_app_id": "1:649679824368:android:0ea5b77ad87ebed922a935",
        "android_client_info": {
          "package_name": "com.tripplanner"
        }
      },
      "oauth_client": [
        {
          "client_id": "649679824368-43ecr8jurs1d3cap40drvdkqrj44nmvq.apps.googleusercontent.com",
          "client_type": 1,
          "android_info": {
            "package_name": "com.tripplanner",
            "certificate_hash": "db68ddafb13164e47fa7e26f95c6db74fe293222"
          }
        },
        {
          "client_id": "649679824368-rpms0cutq5drvcc7tk3omakjiltf8frc.apps.googleusercontent.com",
          "client_type": 1,
          "android_info": {
            "package_name": "com.tripplanner",
            "certificate_hash": "60006e32aee37df5e99cbe2592db6bffdf62db5d"
          }
        },
        {
          "client_id": "649679824368-vi6h1nfb7fvbnjfro352gshhhoqr3v7g.apps.googleusercontent.com",
          "client_type": 1,
          "android_info": {
            "package_name": "com.tripplanner",
            "certificate_hash": "8f7bdd929b824159637b570049040d09579a07a6"
          }
        },
        {
          "client_id": "649679824368-acc2i373pf3bff5ukonh0aos1rjunpo1.apps.googleusercontent.com",
          "client_type": 1,
          "android_info": {
            "package_name": "com.tripplanner",
            "certificate_hash": "a5d174a04aa9f07ccd71fbf2d5e9707e26bcb5c0"
          }
        },
        {
          "client_id": "649679824368-3i9c6t257ct20p7f41ktau40j7hk4i5f.apps.googleusercontent.com",
          "client_type": 1,
          "android_info": {
            "package_name": "com.tripplanner",
            "certificate_hash": "eda3fe9e1dee6f9e4c5ec23f7a58e6ddc24d29c9"
          }
        },
        {
          "client_id": "649679824368-78pr2gqkqme0a3g6q4feetsg07ps4m3j.apps.googleusercontent.com",
          "client_type": 1,
          "android_info": {
            "package_name": "com.tripplanner",
            "certificate_hash": "da092c170bd7dd457491b0a48ead7093efa09d37"
          }
        },
        {
          "client_id": "649679824368-q1sutucacbnmvch5n2ptemqtotvrcoec.apps.googleusercontent.com",
          "client_type": 3
        }
      ],
      "api_key": [
        {
          "current_key": "AIzaSyC77CT8-aL5JxAIVJJqOVMQD1_lHZ-WMok"
        }
      ],
      "services": {
        "appinvite_service": {
          "other_platform_oauth_client": [
            {
              "client_id": "649679824368-q1sutucacbnmvch5n2ptemqtotvrcoec.apps.googleusercontent.com",
              "client_type": 3
            }
          ]
        }
      }
    }
  ],
  "configuration_version": "1"
}